lookat.py
lookat-0.1.0.dist-info/LICENSE
lookat-0.1.0.dist-info/WHEEL
lookat-0.1.0.dist-info/METADATA
lookat-0.1.0.dist-info/RECORD
