Metadata-Version: 2.1
Name: lookat
Version: 0.1.0
Summary: Explore variables during debug
Home-page: UNKNOWN
License: MIT
Author: Antoine Gallix
Author-email: antoine.gallix@gmail.com
Requires-Python: >=3.7,<4.0
Classifier: License :: OSI Approved :: MIT License
Classifier: Programming Language :: Python :: 3
Classifier: Programming Language :: Python :: 3.7
